magicsq/__init__.py
magicsq/bachet_odd.py
magicsq/docs.py
magicsq/eulerbox.py
magicsq/nqueens.py
magicsq-0.1.dist-info/LICENSE
magicsq-0.1.dist-info/METADATA
magicsq-0.1.dist-info/WHEEL
magicsq-0.1.dist-info/entry_points.txt
magicsq-0.1.dist-info/top_level.txt
magicsq-0.1.dist-info/RECORD
