Metadata-Version: 2.1
Name: magicsq
Version: 0.1
Summary: A package for magic squares and N-Queens problem.
Home-page: https://github.com/1darshanpatil/magicsq_project
Author: Darshan Patil
Author-email: drshnp@outlook.com
Classifier: Programming Language :: Python :: 3
Classifier: License :: OSI Approved :: GNU General Public License v3 (GPLv3)
Classifier: Operating System :: OS Independent
License-File: LICENSE
Requires-Dist: numpy
Requires-Dist: pandas
